imagekitcli/__init__.py
imagekitcli/migration.py
imagekit_cli-1.0.5.dist-info/LICENSE
imagekit_cli-1.0.5.dist-info/METADATA
imagekit_cli-1.0.5.dist-info/WHEEL
imagekit_cli-1.0.5.dist-info/entry_points.txt
imagekit_cli-1.0.5.dist-info/top_level.txt
imagekit_cli-1.0.5.dist-info/RECORD
